Metadata-Version: 2.1
Name: northstar
Version: 0.6.0
Summary: Single cell type annotation guided by cell atlases, with freedom to be queer.
Home-page: https://github.com/northstaratlas/northstar
Author: Fabio Zanini
Author-email: fabio.zanini@fastmail.fm
License: MIT
Keywords: graph semi-supervised
Platform: UNKNOWN
Classifier: Development Status :: 4 - Beta
Classifier: Topic :: Utilities
Classifier: License :: OSI Approved :: MIT License
Provides-Extra: atlas-fetcher
License-File: LICENSE
